bargate/__init__.py
bargate/app.py
bargate/defaultcfg.py
bargate/request.py
bargate/doc/bargate.conf.example
bargate/doc/bargate.wsgi.example
bargate/doc/shares.conf.example
bargate/lib/__init__.py
bargate/lib/aes.py
bargate/lib/core.py
bargate/lib/errors.py
bargate/lib/mime.py
bargate/lib/search.py
bargate/lib/smb.py
bargate/lib/totp.py
bargate/lib/user.py
bargate/lib/userdata.py
bargate/static/favicon.ico
bargate/static/css/bargate.css
bargate/static/css/browse-grid.css
bargate/static/css/browse-list.css
bargate/static/css/login.css
bargate/static/images/login.jpg
bargate/static/js/bargate.js
bargate/static/js/browse-grid.js
bargate/static/js/browse-list.js
bargate/static/js/browse-search.js
bargate/static/js/browse.js
bargate/static/js/login.js
bargate/static/js/upload/jquery.dragster.js
bargate/static/js/upload/jquery.fileupload.js
bargate/static/js/upload/jquery.ui.widget.js
bargate/static/themes/cerulean/cerulean.css
bargate/static/themes/cosmo/cosmo.css
bargate/static/themes/cyborg/cyborg.css
bargate/static/themes/darkly/darkly.css
bargate/static/themes/flatly/flatly.css
bargate/static/themes/journal/journal.css
bargate/static/themes/lumen/lumen.css
bargate/static/themes/paper/paper.css
bargate/static/themes/readable/readable.css
bargate/static/themes/sandstone/sandstone.css
bargate/static/themes/simplex/simplex.css
bargate/static/themes/slate/slate.css
bargate/static/themes/spacelab/spacelab.css
bargate/static/themes/united/united.css
bargate/static/themes/yeti/yeti.css
bargate/templates/about.html
bargate/templates/bookmarks-menu.html
bargate/templates/bookmarks.html
bargate/templates/breadcrumbs.html
bargate/templates/changelog.html
bargate/templates/custom.html
bargate/templates/directory-grid.html
bargate/templates/directory-list.html
bargate/templates/directory-menus.html
bargate/templates/directory-modals.html
bargate/templates/dropdown-menus.html
bargate/templates/error.html
bargate-1.5.9.dist-info/DESCRIPTION.rst
bargate-1.5.9.dist-info/METADATA
bargate-1.5.9.dist-info/RECORD
bargate-1.5.9.dist-info/WHEEL
bargate-1.5.9.dist-info/metadata.json
bargate-1.5.9.dist-info/top_level.txt
