Metadata-Version: 2.0
Name: bargate
Version: 1.5.9
Summary: Open source modern web interface for SMB file servers
Home-page: https://bargate.io
Author: David Bell
Author-email: dave@evad.io
License: GNU General Public License v3
Platform: UNKNOWN
Classifier: Environment :: Web Environment
Classifier: Framework :: Flask
Classifier: Intended Audience :: Developers
Classifier: Intended Audience :: Education
Classifier: Intended Audience :: End Users/Desktop
Classifier: Intended Audience :: Information Technology
Classifier: License :: OSI Approved :: GNU General Public License v3 or later (GPLv3+)
Classifier: Operating System :: POSIX :: Linux
Classifier: Programming Language :: Python
Classifier: Programming Language :: Python :: 2
Classifier: Programming Language :: Python :: 2.7
Classifier: Topic :: Internet :: WWW/HTTP
Classifier: Topic :: Internet :: WWW/HTTP :: Dynamic Content
Classifier: Topic :: Communications :: File Sharing
Classifier: Development Status :: 5 - Production/Stable
Classifier: Natural Language :: English
Requires-Dist: Flask (>=0.10)
Requires-Dist: pysmbc (>=1.0.15.5)
Requires-Dist: cryptography (>=2.1.4)
Requires-Dist: Pillow (>=3.0)
Requires-Dist: redis (>=2.4)
